torchvision/_C.so
torchvision/__init__.py
torchvision/_internally_replaced_utils.py
torchvision/_utils.py
torchvision/extension.py
torchvision/image.so
torchvision/utils.py
torchvision/version.py
torchvision/datasets/__init__.py
torchvision/datasets/_optical_flow.py
torchvision/datasets/_stereo_matching.py
torchvision/datasets/caltech.py
torchvision/datasets/celeba.py
torchvision/datasets/cifar.py
torchvision/datasets/cityscapes.py
torchvision/datasets/clevr.py
torchvision/datasets/coco.py
torchvision/datasets/country211.py
torchvision/datasets/dtd.py
torchvision/datasets/eurosat.py
torchvision/datasets/fakedata.py
torchvision/datasets/fer2013.py
torchvision/datasets/fgvc_aircraft.py
torchvision/datasets/flickr.py
torchvision/datasets/flowers102.py
torchvision/datasets/folder.py
torchvision/datasets/food101.py
torchvision/datasets/gtsrb.py
torchvision/datasets/hmdb51.py
torchvision/datasets/imagenet.py
torchvision/datasets/inaturalist.py
torchvision/datasets/kinetics.py
torchvision/datasets/kitti.py
torchvision/datasets/lfw.py
torchvision/datasets/lsun.py
torchvision/datasets/mnist.py
torchvision/datasets/omniglot.py
torchvision/datasets/oxford_iiit_pet.py
torchvision/datasets/pcam.py
torchvision/datasets/phototour.py
torchvision/datasets/places365.py
torchvision/datasets/rendered_sst2.py
torchvision/datasets/sbd.py
torchvision/datasets/sbu.py
torchvision/datasets/semeion.py
torchvision/datasets/stanford_cars.py
torchvision/datasets/stl10.py
torchvision/datasets/sun397.py
torchvision/datasets/svhn.py
torchvision/datasets/ucf101.py
torchvision/datasets/usps.py
torchvision/datasets/utils.py
torchvision/datasets/video_utils.py
torchvision/datasets/vision.py
torchvision/datasets/voc.py
torchvision/datasets/widerface.py
torchvision/datasets/samplers/__init__.py
torchvision/datasets/samplers/clip_sampler.py
torchvision/io/__init__.py
torchvision/io/_load_gpu_decoder.py
torchvision/io/_video_opt.py
torchvision/io/image.py
torchvision/io/video.py
torchvision-0.14.0a0+ebeef87.dist-info/LICENSE
torchvision-0.14.0a0+ebeef87.dist-info/METADATA
torchvision-0.14.0a0+ebeef87.dist-info/WHEEL
torchvision-0.14.0a0+ebeef87.dist-info/top_level.txt
torchvision-0.14.0a0+ebeef87.dist-info/RECORD
