Metadata-Version: 2.1
Name: torchvision_abi
Version: 0.14.0a0
Summary: image and video datasets and models for torch deep learning
Home-page: https://github.com/pytorch/vision
Author: PyTorch Core Team
Author-email: soumith@pytorch.org
License: BSD
Requires-Python: >=3.7
License-File: LICENSE
Requires-Dist: typing-extensions
Requires-Dist: numpy
Requires-Dist: requests
Requires-Dist: pillow !=8.3.*,>=5.3.0
Provides-Extra: scipy
Requires-Dist: scipy ; extra == 'scipy'
